sioba/__init__.py
sioba/__init__.pyi
sioba/buffer/__init__.py
sioba/buffer/base.py
sioba/buffer/line.py
sioba/buffer/terminal.py
sioba/context.py
sioba/errors.py
sioba/interface/__init__.py
sioba/interface/base.py
sioba/interface/echo.py
sioba/interface/function.py
sioba/interface/io.py
sioba/interface/socket.py
sioba/io.py
sioba/py.typed
sioba-0.6.20251011.dist-info/WHEEL
sioba-0.6.20251011.dist-info/entry_points.txt
sioba-0.6.20251011.dist-info/METADATA
sioba-0.6.20251011.dist-info/RECORD
