Metadata-Version: 2.3
Name: sioba
Version: 0.6.20251011
Summary: Sioba IO Abstraction Layer
License: MIT License
Classifier: License :: OSI Approved :: MIT License
Requires-Dist: loguru>=0.7.2
Requires-Dist: rich>=14.0.0
Requires-Dist: pyte>=0.8.2
Requires-Dist: janus>=2.0.0
Requires-Python: >=3.10
Project-URL: Homepage, https://github.com/amimoto/sioba
Project-URL: Issues, https://github.com/amimoto/sioba/issues
